simpleWebBrowsing/__init__.py
simpleWebBrowsing/chromeConfig.py
simpleWebBrowsing/seleniumNew/__init__.py
simpleWebBrowsing/seleniumNew/chromeNav.py
simpleWebBrowsing/seleniumNew/elementsNav.py
simpleWebBrowsing/seleniumOld/__init__.py
simpleWebBrowsing/seleniumOld/chromeNav.py
simpleWebBrowsing/seleniumOld/elementsNav.py
simpleWebBrowsing-1.3.1.dist-info/METADATA
simpleWebBrowsing-1.3.1.dist-info/WHEEL
simpleWebBrowsing-1.3.1.dist-info/top_level.txt
simpleWebBrowsing-1.3.1.dist-info/RECORD
